pycov
