Metadata-Version: 1.2
Name: pycov
Version: 1.3
Summary: A library getting how many people are now ill with coronavirus
Home-page: https://pypi.org/project/pycov/
Author: kewldan
Author-email: kewldanil1@gmail.com
License: UNKNOWN
Platform: UNKNOWN
Requires-Python: >=3.6
